{
  "swagger": "2.0",
  "info": {
    "title": "User API",
    "description": "User API",
    "version": "1.0.0"
  },
  "host": "localhost:8080",
  "basePath": "/",
  "schemes": [
    "https",
    "http"
  ],
  "paths": {
    "/clients/": {
      "get": {
        "description": "Get all the clients",
        "produces": [
          "application/json"
        ],
        "responses": {
          "200": {
            "description": "OK"
          }
        }
      },
      "post": {
        "description": "Add a new client to the database",
        "parameters": [
          {
            "name": "body",
            "in": "body",
            "schema": {
              "type": "object",
              "properties": {
                "firstName": {
                  "example": "any"
                },
                "lastName": {
                  "example": "any"
                },
                "email": {
                  "example": "any"
                },
                "favoriteColor": {
                  "example": "any"
                },
                "lastPurchase": {
                  "example": "any"
                }
              }
            }
          }
        ],
        "responses": {
          "204": {
            "description": "No Content"
          },
          "500": {
            "description": "Internal Server Error"
          }
        }
      }
    },
    "/clients/{id}": {
      "get": {
        "description": "Get a specific client from database",
        "produces": [
          "application/json"
        ],
        "parameters": [
          {
            "name": "id",
            "in": "path",
            "required": true,
            "type": "string"
          }
        ],
        "responses": {
          "200": {
            "description": "OK"
          }
        }
      },
      "put": {
        "description": "Update a client from the database",
        "parameters": [
          {
            "name": "id",
            "in": "path",
            "required": true,
            "type": "string"
          },
          {
            "name": "body",
            "in": "body",
            "schema": {
              "type": "object",
              "properties": {
                "firstName": {
                  "example": "any"
                },
                "lastName": {
                  "example": "any"
                },
                "email": {
                  "example": "any"
                },
                "favoriteColor": {
                  "example": "any"
                },
                "lastPurchase": {
                  "example": "any"
                }
              }
            }
          }
        ],
        "responses": {
          "204": {
            "description": "No Content"
          },
          "500": {
            "description": "Internal Server Error"
          }
        }
      },
      "delete": {
        "description": "Delete a client from database",
        "parameters": [
          {
            "name": "id",
            "in": "path",
            "required": true,
            "type": "string"
          }
        ],
        "responses": {
          "204": {
            "description": "No Content"
          },
          "500": {
            "description": "Internal Server Error"
          }
        }
      }
    },
    "/products/": {
      "get": {
        "description": "Get all products from database",
        "produces": [
          "application/json"
        ],
        "responses": {
          "200": {
            "description": "OK"
          }
        }
      },
      "post": {
        "description": "Add a new product to database",
        "parameters": [
          {
            "name": "body",
            "in": "body",
            "schema": {
              "type": "object",
              "properties": {
                "productName": {
                  "example": "any"
                },
                "productCost": {
                  "example": "any"
                }
              }
            }
          }
        ],
        "responses": {
          "204": {
            "description": "No Content"
          },
          "500": {
            "description": "Internal Server Error"
          }
        }
      }
    },
    "/products/{id}": {
      "get": {
        "description": "Get a specific product from database",
        "produces": [
          "application/json"
        ],
        "parameters": [
          {
            "name": "id",
            "in": "path",
            "required": true,
            "type": "string"
          }
        ],
        "responses": {
          "200": {
            "description": "OK"
          }
        }
      },
      "put": {
        "description": "Update a product from database",
        "parameters": [
          {
            "name": "id",
            "in": "path",
            "required": true,
            "type": "string"
          },
          {
            "name": "body",
            "in": "body",
            "schema": {
              "type": "object",
              "properties": {
                "productName": {
                  "example": "any"
                },
                "productCost": {
                  "example": "any"
                }
              }
            }
          }
        ],
        "responses": {
          "204": {
            "description": "No Content"
          },
          "500": {
            "description": "Internal Server Error"
          }
        }
      },
      "delete": {
        "description": "Delete a product from database",
        "parameters": [
          {
            "name": "id",
            "in": "path",
            "required": true,
            "type": "string"
          }
        ],
        "responses": {
          "204": {
            "description": "No Content"
          },
          "500": {
            "description": "Internal Server Error"
          }
        }
      }
    }
  }
}